{
  "$schema": "https://vega.github.io/schema/vega-lite/v5.17.0.json",
  "config": {
    "axis": {
      "domainColor": "#666666",
      "gridColor": "#666666",
      "labelColor": "#DBDEE1",
      "tickColor": "#DBDEE1",
      "titleColor": "#DBDEE1"
    },
    "background": "transparent",
    "legend": {
      "labelColor": "#DBDEE1",
      "titleColor": "#DBDEE1"
    },
    "title": {
      "color": "#DBDEE1",
      "fontSize": 16
    }
  },
  "data": {
    "name": "data-d0acfd1a75be08a368ff6a4d03adefda"
  },
  "datasets": {
    "data-d0acfd1a75be08a368ff6a4d03adefda": [
      {
        "duration_in_seconds": 26.630239520958085,
        "lustrum": "1980_1984"
      },
      {
        "duration_in_seconds": 26.379196021549937,
        "lustrum": "1985_1989"
      },
      {
        "duration_in_seconds": 23.99565972222222,
        "lustrum": "1990_1994"
      },
      {
        "duration_in_seconds": 24.197831978319783,
        "lustrum": "1995_1999"
      },
      {
        "duration_in_seconds": 23.0206008583691,
        "lustrum": "2000_2004"
      },
      {
        "duration_in_seconds": 21.829931972789115,
        "lustrum": "2005_2009"
      },
      {
        "duration_in_seconds": 24.547752808988765,
        "lustrum": "2010_2014"
      },
      {
        "duration_in_seconds": 23.82262996941896,
        "lustrum": "2015_2019"
      },
      {
        "duration_in_seconds": 22.743875278396438,
        "lustrum": "2020_2024"
      }
    ]
  },
  "height": "container",
  "layer": [
    {
      "encoding": {
        "tooltip": [
          {
            "field": "lustrum",
            "type": "ordinal"
          },
          {
            "field": "duration_in_seconds",
            "type": "quantitative"
          }
        ],
        "x": {
          "axis": {
            "labelAngle": 0
          },
          "field": "lustrum",
          "title": "",
          "type": "ordinal"
        },
        "y": {
          "field": "duration_in_seconds",
          "scale": {
            "domain": [
              21.349901217972217,
              27.110270275774983
            ]
          },
          "title": "Durata media (s)",
          "type": "quantitative"
        }
      },
      "mark": {
        "interpolate": "monotone",
        "type": "line"
      }
    },
    {
      "encoding": {
        "tooltip": [
          {
            "field": "lustrum",
            "type": "ordinal"
          },
          {
            "field": "duration_in_seconds",
            "format": ".2f",
            "type": "quantitative"
          }
        ],
        "x": {
          "field": "lustrum",
          "type": "ordinal"
        },
        "y": {
          "field": "duration_in_seconds",
          "type": "quantitative"
        }
      },
      "mark": {
        "type": "point"
      }
    }
  ],
  "width": "container"
}