{"config": {"background": "transparent", "title": {"color": "#DBDEE1", "fontSize": 16}, "axis": {"domainColor": "#666666", "gridColor": "#666666", "tickColor": "#DBDEE1", "titleColor": "#DBDEE1", "labelColor": "#DBDEE1"}, "legend": {"labelColor": "#DBDEE1", "titleColor": "#DBDEE1"}, "point": {"size": 80}, "view": {"strokeWidth": 0}}, "layer": [{"data": {"name": "data-4e4315e4ae7feb227de911033f404cc8"}, "mark": {"type": "rule", "strokeWidth": 4}, "encoding": {"color": {"field": "value", "legend": null, "scale": {"scheme": "sinebow"}, "type": "quantitative"}, "y": {"axis": null, "field": "index", "type": "quantitative"}}, "transform": [{"window": [{"op": "count", "as": "index"}]}]}, {"data": {"name": "data-20d91d149267c5e899aa701b19943927"}, "mark": {"type": "line", "color": "rgba(256,256,256,.5)", "interpolate": "monotone", "point": {"color": "white"}, "strokeWidth": 4}, "encoding": {"detail": {"field": "index", "type": "nominal"}, "x": {"axis": {"labelAngle": 0, "title": null}, "field": "key", "scale": {"padding": 0}, "type": "nominal"}, "y": {"axis": {"orient": "right", "title": null}, "field": "value", "scale": {"domain": [0, 1]}, "type": "quantitative"}}, "transform": [{"window": [{"op": "count", "as": "index"}]}, {"fold": ["hue 1", "hue 2", "hue 3", "hue 4", "hue 5"]}]}, {"data": {"name": "data-381ad2edaab94d3fd8d44868d9a7a21c"}, "mark": {"type": "text", "color": "white", "dx": -8, "dy": -8}, "encoding": {"text": {"field": "Cluster", "type": "nominal"}, "x": {"value": 0}, "y": {"axis": null, "field": "hue 1", "scale": {"domain": [0, 1]}, "type": "quantitative"}}}], "height": "container", "resolve": {"scale": {"y": "independent"}}, "width": "container", "$schema": "https://vega.github.io/schema/vega-lite/v5.17.0.json", "datasets": {"data-4e4315e4ae7feb227de911033f404cc8": [{"value": 0.0}, {"value": 0.1111111111111111}, {"value": 0.2222222222222222}, {"value": 0.3333333333333333}, {"value": 0.4444444444444444}, {"value": 0.5555555555555556}, {"value": 0.6666666666666666}, {"value": 0.7777777777777777}, {"value": 0.8888888888888888}, {"value": 1.0}], "data-20d91d149267c5e899aa701b19943927": [{"Cluster": "A", "hue 1": 0.0975073874761859, "hue 2": 0.1532815993442413, "hue 3": 0.090073552774566, "hue 4": 0.089027776410165, "hue 5": 0.0874059757166321}, {"Cluster": "B", "hue 1": 0.1341406039153727, "hue 2": 0.2753352188418917, "hue 3": 0.1903371277900356, "hue 4": 0.7258169844359544, "hue 5": 0.2139854121893843}, {"Cluster": "C", "hue 1": 0.2618825525749053, "hue 2": 0.2379018498825016, "hue 3": 0.2060939603156932, "hue 4": 0.1321746619454922, "hue 5": 0.7115733902252679}, {"Cluster": "D", "hue 1": 0.5800639042866473, "hue 2": 0.5813059337174934, "hue 3": 0.5663857142085261, "hue 4": 0.5710249772097262, "hue 5": 0.5565762927544237}, {"Cluster": "E", "hue 1": 0.3234554321982628, "hue 2": 0.274285732661315, "hue 3": 0.6984243014508327, "hue 4": 0.167076100219503, "hue 5": 0.1189660241516175}, {"Cluster": "F", "hue 1": 0.7030101239635936, "hue 2": 0.2835670405043016, "hue 3": 0.1046012478954382, "hue 4": 0.227325678485114, "hue 5": 0.1044573373032137}], "data-381ad2edaab94d3fd8d44868d9a7a21c": [{"Cluster": "A", "hue 1": 0.0975073874761859}, {"Cluster": "B", "hue 1": 0.1341406039153727}, {"Cluster": "C", "hue 1": 0.2618825525749053}, {"Cluster": "D", "hue 1": 0.5800639042866473}, {"Cluster": "E", "hue 1": 0.3234554321982628}, {"Cluster": "F", "hue 1": 0.7030101239635936}]}}