{"config": {"background": "#313338", "title": {"color": "#DBDEE1", "fontSize": 16}, "axis": {"domainColor": "#B0B0B0", "gridColor": "#333333", "tickColor": "#B0B0B0", "titleColor": "#DBDEE1", "labelColor": "#DBDEE1"}, "legend": {"labelColor": "#DBDEE1", "titleColor": "#DBDEE1"}}, "data": {"name": "data-5f2d8c6309d56f41d95fbc9d60c53690"}, "mark": {"type": "bar", "tooltip": true}, "encoding": {"color": {"field": "closest_cm_hex_color", "scale": null, "type": "nominal"}, "x": {"field": "cw_tf_idf_norm", "title": null, "type": "quantitative"}, "y": {"field": "closest_cm_color_name", "sort": "-x", "title": null, "type": "nominal"}}, "height": "container", "transform": [{"window": [{"op": "rank", "field": "cw_tf_idf_norm", "as": "rank"}], "sort": [{"field": "cw_tf_idf_norm", "order": "descending"}]}, {"filter": "(datum.rank <= 5)"}], "width": "container", "$schema": "https://vega.github.io/schema/vega-lite/v5.17.0.json", "datasets": {"data-5f2d8c6309d56f41d95fbc9d60c53690": [{"closest_cm_color_name": "bone", "closest_cm_hex_color": "#E7DECC", "cw_tf_idf": 0.002814270118926527, "cw_tf_idf_norm": 0.08574368405878277}, {"closest_cm_color_name": "brown_oil", "closest_cm_hex_color": "#231709", "cw_tf_idf": 0.003311337854498869, "cw_tf_idf_norm": 0.10186337349147193}, {"closest_cm_color_name": "charcoal", "closest_cm_hex_color": "#28231D", "cw_tf_idf": 0.003204264449977804, "cw_tf_idf_norm": 0.09839102977680113}, {"closest_cm_color_name": "cloud", "closest_cm_hex_color": "#C5C6D0", "cw_tf_idf": 0.0009340798953845378, "cw_tf_idf_norm": 0.024769936802833008}, {"closest_cm_color_name": "coal", "closest_cm_hex_color": "#0C0908", "cw_tf_idf": 0.0010529949474883725, "cw_tf_idf_norm": 0.028626299973495667}, {"closest_cm_color_name": "cool_black", "closest_cm_hex_color": "#151922", "cw_tf_idf": 0.000450741670151627, "cw_tf_idf_norm": 0.009095489390287648}, {"closest_cm_color_name": "crow", "closest_cm_hex_color": "#0D0907", "cw_tf_idf": 0.0034813876866933713, "cw_tf_idf_norm": 0.10737801523320561}, {"closest_cm_color_name": "dark_raisin", "closest_cm_hex_color": "#1A0F0F", "cw_tf_idf": 0.0008654081074176916, "cw_tf_idf_norm": 0.022542940730479938}, {"closest_cm_color_name": "dark_silver", "closest_cm_hex_color": "#746D69", "cw_tf_idf": 0.010498113377491387, "cw_tf_idf_norm": 0.3349273628886095}, {"closest_cm_color_name": "dim_gray", "closest_cm_hex_color": "#696969", "cw_tf_idf": 0.0019139809173493528, "cw_tf_idf_norm": 0.056547698702143934}, {"closest_cm_color_name": "dull_black", "closest_cm_hex_color": "#161616", "cw_tf_idf": 0.0020075154775123466, "cw_tf_idf_norm": 0.0595809836111203}, {"closest_cm_color_name": "fossil", "closest_cm_hex_color": "#787276", "cw_tf_idf": 0.00017027259945202365, "cw_tf_idf_norm": 0.0}, {"closest_cm_color_name": "gray", "closest_cm_hex_color": "#808080", "cw_tf_idf": 0.00031712849255708617, "cw_tf_idf_norm": 0.0047624724334361405}, {"closest_cm_color_name": "gray_dolphin", "closest_cm_hex_color": "#5C5858", "cw_tf_idf": 0.0007832910939897874, "cw_tf_idf_norm": 0.019879921872348615}, {"closest_cm_color_name": "gray_wolf", "closest_cm_hex_color": "#504A4B", "cw_tf_idf": 0.003992813636090489, "cw_tf_idf_norm": 0.12396333526530799}, {"closest_cm_color_name": "grease", "closest_cm_hex_color": "#0A0806", "cw_tf_idf": 0.0012754085723412772, "cw_tf_idf_norm": 0.035839076626760606}, {"closest_cm_color_name": "gunmetal", "closest_cm_hex_color": "#2A3439", "cw_tf_idf": 0.00023792439707745968, "cw_tf_idf_norm": 0.002193918231344254}, {"closest_cm_color_name": "iron", "closest_cm_hex_color": "#322D31", "cw_tf_idf": 0.0021592382752477217, "cw_tf_idf_norm": 0.06450128763474972}, {"closest_cm_color_name": "leather", "closest_cm_hex_color": "#0B0705", "cw_tf_idf": 0.0012444760168179492, "cw_tf_idf_norm": 0.03483594736949484}, {"closest_cm_color_name": "metal", "closest_cm_hex_color": "#0E0C0A", "cw_tf_idf": 0.0007197316974945947, "cw_tf_idf_norm": 0.017818718421169184}, {"closest_cm_color_name": "misty_gray", "closest_cm_hex_color": "#BCC2C2", "cw_tf_idf": 0.01607986615915988, "cw_tf_idf_norm": 0.5159411662225617}, {"closest_cm_color_name": "neutral_black", "closest_cm_hex_color": "#0B0B0B", "cw_tf_idf": 0.002892096961326792, "cw_tf_idf_norm": 0.08826757454540747}, {"closest_cm_color_name": "nevada", "closest_cm_hex_color": "#666A6D", "cw_tf_idf": 0.0013065153338264167, "cw_tf_idf_norm": 0.03684785530723524}, {"closest_cm_color_name": "outer_space", "closest_cm_hex_color": "#414A4C", "cw_tf_idf": 0.008494614060404637, "cw_tf_idf_norm": 0.2699547556183818}, {"closest_cm_color_name": "pastel_gray", "closest_cm_hex_color": "#CCCDC6", "cw_tf_idf": 0.004087374538159725, "cw_tf_idf_norm": 0.12702990399376488}, {"closest_cm_color_name": "peanut_brown", "closest_cm_hex_color": "#795C34", "cw_tf_idf": 0.0015978819132081476, "cw_tf_idf_norm": 0.046296746141580934}, {"closest_cm_color_name": "pebble", "closest_cm_hex_color": "#333333", "cw_tf_idf": 0.0004973171292167271, "cw_tf_idf_norm": 0.010605911173045003}, {"closest_cm_color_name": "pecan", "closest_cm_hex_color": "#4A2511", "cw_tf_idf": 0.0017181276511312217, "cw_tf_idf_norm": 0.050196262871816166}, {"closest_cm_color_name": "perfect_gray", "closest_cm_hex_color": "#A1A1A1", "cw_tf_idf": 0.00018526941147115706, "cw_tf_idf_norm": 0.00048634005977172846}, {"closest_cm_color_name": "raisin", "closest_cm_hex_color": "#290916", "cw_tf_idf": 0.0004044753308119595, "cw_tf_idf_norm": 0.007595092225132462}, {"closest_cm_color_name": "raisin_black", "closest_cm_hex_color": "#242124", "cw_tf_idf": 0.0014761464609228906, "cw_tf_idf_norm": 0.042348918625625225}, {"closest_cm_color_name": "retro_black", "closest_cm_hex_color": "#1F201F", "cw_tf_idf": 0.0021710813018878316, "cw_tf_idf_norm": 0.06488535181296845}, {"closest_cm_color_name": "roasted_coffee", "closest_cm_hex_color": "#4B371C", "cw_tf_idf": 0.0012874752011046956, "cw_tf_idf_norm": 0.036230392124118105}, {"closest_cm_color_name": "shadow", "closest_cm_hex_color": "#373737", "cw_tf_idf": 0.0056150022967372355, "cw_tf_idf_norm": 0.17657020459016248}, {"closest_cm_color_name": "silver_chalice", "closest_cm_hex_color": "#ACACAC", "cw_tf_idf": 0.00022731738789335165, "cw_tf_idf_norm": 0.001849937559050913}, {"closest_cm_color_name": "spanish_gray", "closest_cm_hex_color": "#989898", "cw_tf_idf": 0.007422974677262677, "cw_tf_idf_norm": 0.23520195875821845}, {"closest_cm_color_name": "stone_gray", "closest_cm_hex_color": "#928E85", "cw_tf_idf": 0.031006334153115548, "cw_tf_idf_norm": 1.0}, {"closest_cm_color_name": "taupe", "closest_cm_hex_color": "#483C32", "cw_tf_idf": 0.0024916700855436924, "cw_tf_idf_norm": 0.07528190596103775}, {"closest_cm_color_name": "tea_bag", "closest_cm_hex_color": "#161311", "cw_tf_idf": 0.0006384842247559869, "cw_tf_idf_norm": 0.015183898387579156}, {"closest_cm_color_name": "tech_black", "closest_cm_hex_color": "#0D0E0E", "cw_tf_idf": 0.0006517445466238854, "cw_tf_idf_norm": 0.015613924830639071}, {"closest_cm_color_name": "vintage_gray", "closest_cm_hex_color": "#989692", "cw_tf_idf": 0.0002682480485110624, "cw_tf_idf_norm": 0.0031773009950876382}, {"closest_cm_color_name": "zombie_gray", "closest_cm_hex_color": "#63645E", "cw_tf_idf": 0.0008959893124784516, "cw_tf_idf_norm": 0.023534675845794193}]}}